{"is_source_file": true, "format": "TypeScript/JavaScript with React (TSX)", "description": "A React component implementing a global error boundary for Next.js's App Router, capturing runtime errors in segments and providing a retry mechanism.", "external_files": [], "external_methods": ["console.error"], "published": [], "classes": [], "methods": [{"name": "GlobalError", "description": "React component that displays an error message when a runtime error occurs, and provides a reset callback to retry rendering."}], "calls": ["React.useEffect", "console.error"], "search-terms": ["GlobalError", "error boundary", "Next.js App Router", "error handling", "React"], "state": 2, "file_id": 33, "knowledge_revision": 126, "git_revision": "872deb14f16059ceb5eeb8911d0e2e6ef815c058", "revision_history": [{"117": ""}, {"126": "872deb14f16059ceb5eeb8911d0e2e6ef815c058"}], "ctags": [], "hash": "c07dabb5b39e7eae2d2dd04ac20ac44e", "format-version": 4, "code-base-name": "nextjs_frontend", "filename": "nextjs_frontend/src/app/error.tsx"}